huntinghorn/__init__.py
huntinghorn/constants.py
huntinghorn/data/horns.json
huntinghorn/data/melodies.json
huntinghorn/prompt.py
huntinghorn/utils.py
huntinghorn-0.3.1.dist-info/entry_points.txt
huntinghorn-0.3.1.dist-info/WHEEL
huntinghorn-0.3.1.dist-info/METADATA
huntinghorn-0.3.1.dist-info/RECORD
