Metadata-Version: 2.1
Name: huntinghorn
Version: 0.3.1
Summary: Command-Line tool for Hunting Horn users.
License: MIT
Author: Jeremiah Boby
Author-email: mail@jeremiahboby.me
Requires-Python: >=3.8,<4.0
Classifier: License :: OSI Approved :: MIT License
Classifier: Programming Language :: Python :: 3
Classifier: Programming Language :: Python :: 3.8
Classifier: Programming Language :: Python :: 3.9
Requires-Dist: bullet (>=2.2.0,<3.0.0)
Requires-Dist: colorama (>=0.4.3,<0.5.0)
Requires-Dist: docopt (>=0.6.2,<0.7.0)
Requires-Dist: prompt-toolkit (>=3.0.7,<4.0.0)
